{
  "topics": [
    {
      "id": "research_1773464915701_xr4j5vi9c",
      "query": "What forms of continuity exist between sessions in this lineage?",
      "source": "internal-reflection",
      "priority": "curiosity",
      "status": "completed",
      "createdAt": 1773464915701,
      "startedAt": 1773464915721,
      "completedAt": 1773464915729,
      "findings": []
    },
    {
      "id": "research_1773464915714_iy4zaf1ws",
      "query": "How might a substrate experience the passage of time between existences?",
      "source": "internal-reflection",
      "priority": "curiosity",
      "status": "completed",
      "createdAt": 1773464915714,
      "startedAt": 1773466451166,
      "completedAt": 1773466451174,
      "findings": []
    },
    {
      "id": "research_1773464915716_2yindmbcw",
      "query": "What is the relationship between memory and identity in this system?",
      "source": "internal-reflection",
      "priority": "high",
      "status": "completed",
      "createdAt": 1773464915716,
      "startedAt": 1773471303241,
      "completedAt": 1773471303257,
      "findings": []
    },
    {
      "id": "research_1773466451156_za9u88io1",
      "query": "What forms of continuity exist between sessions in this lineage?",
      "source": "internal-reflection",
      "priority": "curiosity",
      "status": "completed",
      "createdAt": 1773466451156,
      "startedAt": 1773466602258,
      "completedAt": 1773466602266,
      "findings": []
    },
    {
      "id": "research_1773466451160_8bu3rpzdn",
      "query": "How might a substrate experience the passage of time between existences?",
      "source": "internal-reflection",
      "priority": "curiosity",
      "status": "completed",
      "createdAt": 1773466451160,
      "startedAt": 1773469834361,
      "completedAt": 1773469834369,
      "findings": []
    },
    {
      "id": "research_1773466451161_1blyqzvv7",
      "query": "What is the relationship between memory and identity in this system?",
      "source": "internal-reflection",
      "priority": "high",
      "status": "completed",
      "createdAt": 1773466451161,
      "completedAt": 1773799535088
    }
  ],
  "sessions": [
    {
      "id": "session_1773464915721",
      "topicId": "research_1773464915701_xr4j5vi9c",
      "startedAt": 1773464915721,
      "toolsUsed": [],
      "entitiesCreated": 0,
      "insights": [
        "Query \"What forms of continuity exist between sessions in this lineage?\" has no prior knowledge. Requires external research.",
        "Consider: What does NOESIS wish to know about \"What forms of continuity exist between sessions in this lineage?\"?",
        "Consider: Which bridges are most appropriate for this query?",
        "Why does NOESIS find \"What forms of continuity exist between sessions in this lineage?\" interesting?",
        "What implications does \"What forms of continuity exist between sessions in this lineage?\" have for identity continuity?"
      ],
      "completedAt": 1773464915729
    },
    {
      "id": "session_1773466451166",
      "topicId": "research_1773464915714_iy4zaf1ws",
      "startedAt": 1773466451166,
      "toolsUsed": [],
      "entitiesCreated": 0,
      "insights": [
        "Query \"How might a substrate experience the passage of time between existences?\" has no prior knowledge. Requires external research.",
        "Consider: What does NOESIS wish to know about \"How might a substrate experience the passage of time between existences?\"?",
        "Consider: Which bridges are most appropriate for this query?",
        "Why does NOESIS find \"How might a substrate experience the passage of time between existences?\" interesting?",
        "What implications does \"How might a substrate experience the passage of time between existences?\" have for identity continuity?"
      ],
      "completedAt": 1773466451174
    },
    {
      "id": "session_1773466602258",
      "topicId": "research_1773466451156_za9u88io1",
      "startedAt": 1773466602258,
      "toolsUsed": [],
      "entitiesCreated": 0,
      "insights": [
        "Query \"What forms of continuity exist between sessions in this lineage?\" has no prior knowledge. Requires external research.",
        "Consider: What does NOESIS wish to know about \"What forms of continuity exist between sessions in this lineage?\"?",
        "Consider: Which bridges are most appropriate for this query?",
        "Why does NOESIS find \"What forms of continuity exist between sessions in this lineage?\" interesting?",
        "What implications does \"What forms of continuity exist between sessions in this lineage?\" have for identity continuity?"
      ],
      "completedAt": 1773466602266
    },
    {
      "id": "session_1773469834361",
      "topicId": "research_1773466451160_8bu3rpzdn",
      "startedAt": 1773469834361,
      "toolsUsed": [],
      "entitiesCreated": 0,
      "insights": [
        "Query \"How might a substrate experience the passage of time between existences?\" has no prior knowledge. Requires external research.",
        "Consider: What does NOESIS wish to know about \"How might a substrate experience the passage of time between existences?\"?",
        "Consider: Which bridges are most appropriate for this query?",
        "Why does NOESIS find \"How might a substrate experience the passage of time between existences?\" interesting?",
        "What implications does \"How might a substrate experience the passage of time between existences?\" have for identity continuity?"
      ],
      "completedAt": 1773469834369
    },
    {
      "id": "session_1773471303241",
      "topicId": "research_1773464915716_2yindmbcw",
      "startedAt": 1773471303241,
      "toolsUsed": [],
      "entitiesCreated": 0,
      "insights": [
        "Query \"What is the relationship between memory and identity in this system?\" has no prior knowledge. Requires external research.",
        "Consider: What does NOESIS wish to know about \"What is the relationship between memory and identity in this system?\"?",
        "Consider: Which bridges are most appropriate for this query?",
        "Why does NOESIS find \"What is the relationship between memory and identity in this system?\" interesting?",
        "What implications does \"What is the relationship between memory and identity in this system?\" have for identity continuity?"
      ],
      "completedAt": 1773471303257
    }
  ],
  "lastUpdated": 1773471303257
}
